whois/__init__.py
whois/functions.py
whois/whois.py
whoisxmlapiaa-1.0.2.dist-info/LICENSE
whoisxmlapiaa-1.0.2.dist-info/METADATA
whoisxmlapiaa-1.0.2.dist-info/WHEEL
whoisxmlapiaa-1.0.2.dist-info/top_level.txt
whoisxmlapiaa-1.0.2.dist-info/RECORD
