Metadata-Version: 2.1
Name: whoisxmlapiaa
Version: 1.0.2
Summary: App that print info about website from whoisxmlapi.
Home-page: https://github.com/pypa/sampleproject
Author: Vojtech Zamecnik
Author-email: vojta.zamecnik@seznam.cz
License: UNKNOWN
Platform: UNKNOWN
Classifier: Programming Language :: Python :: 3
Classifier: License :: OSI Approved :: MIT License
Classifier: Operating System :: OS Independent
